{
	"id": "b8eef0c5-eef2-400a-a675-e995a7545df2",
	"name": "booking",
	"values": [
		{
			"key": "main_url",
			"value": "https://restful-booker.herokuapp.com",
			"type": "default",
			"enabled": true
		},
		{
			"key": "firstname",
			"value": "",
			"type": "any",
			"enabled": true
		},
		{
			"key": "lastname",
			"value": "",
			"type": "any",
			"enabled": true
		},
		{
			"key": "totalprice",
			"value": "",
			"type": "any",
			"enabled": true
		},
		{
			"key": "depositpaid",
			"value": "",
			"type": "any",
			"enabled": true
		},
		{
			"key": "checkin",
			"value": "",
			"type": "any",
			"enabled": true
		},
		{
			"key": "checkout",
			"value": "",
			"type": "any",
			"enabled": true
		},
		{
			"key": "token",
			"value": "",
			"type": "any",
			"enabled": true
		},
		{
			"key": "id",
			"value": "",
			"type": "any",
			"enabled": true
		},
		{
			"key": "update_firstName",
			"value": "",
			"type": "any",
			"enabled": true
		},
		{
			"key": "update_lastName",
			"value": "",
			"type": "any",
			"enabled": true
		},
		{
			"key": "update_randomPrice",
			"value": "",
			"type": "any",
			"enabled": true
		},
		{
			"key": "update_randomBoolean",
			"value": "",
			"type": "any",
			"enabled": true
		},
		{
			"key": "update_checkin",
			"value": "",
			"type": "any",
			"enabled": true
		},
		{
			"key": "update_checkout",
			"value": "",
			"type": "any",
			"enabled": true
		},
		{
			"key": "update_firstname",
			"value": "",
			"type": "any",
			"enabled": true
		},
		{
			"key": "updated_firstname",
			"value": "",
			"type": "any",
			"enabled": true
		},
		{
			"key": "updated_lastname",
			"value": "",
			"type": "any",
			"enabled": true
		},
		{
			"key": "updated_totalprice",
			"value": "",
			"type": "any",
			"enabled": true
		},
		{
			"key": "updated_depositpaid",
			"value": "",
			"type": "any",
			"enabled": true
		},
		{
			"key": "updated_checkin",
			"value": "",
			"type": "any",
			"enabled": true
		},
		{
			"key": "updated_checkout",
			"value": "",
			"type": "any",
			"enabled": true
		}
	],
	"_postman_variable_scope": "environment",
	"_postman_exported_at": "2024-09-06T11:48:59.164Z",
	"_postman_exported_using": "Postman/11.11.1"
}